discord_webhook/__init__.py
discord_webhook/__main__.py
discord_webhook/async_webhook.py
discord_webhook/constants.py
discord_webhook/webhook.py
discord_webhook/webhook_exceptions.py
discord_webhook-1.4.0.dist-info/entry_points.txt
discord_webhook-1.4.0.dist-info/LICENSE
discord_webhook-1.4.0.dist-info/METADATA
discord_webhook-1.4.0.dist-info/WHEEL
discord_webhook-1.4.0.dist-info/RECORD
