Metadata-Version: 2.1
Name: discord-webhook
Version: 1.4.0
Summary: Easily send Discord webhooks with Python
Home-page: https://github.com/lovvskillz/python-discord-webhook
License: MIT
Keywords: discord,webhook
Author: lovvskillz
Author-email: 14542790+lovvskillz@users.noreply.github.com
Requires-Python: >=3.10,<4.0
Classifier: License :: OSI Approved :: MIT License
Classifier: Programming Language :: Python :: 3
Classifier: Programming Language :: Python :: 3.10
Classifier: Programming Language :: Python :: 3.11
Provides-Extra: async
Requires-Dist: httpx (>=0.28.1,<0.29.0) ; extra == "async"
Requires-Dist: requests (==2.32.0)
Project-URL: Repository, https://github.com/lovvskillz/python-discord-webhook
